Metadata-Version: 2.2
Name: loss_adapted_plasticity
Version: 0.1.8
Summary: A python package for training neural networks on noisy data sources
Home-page: https://github.com/alexcapstick/loss_adapted_plasticity
Author: Alexander Capstick
Author-email: alexander.capstick19@imperial.ac.uk
License: MIT
Classifier: Intended Audience :: Science/Research
Classifier: Programming Language :: Python :: 3
Classifier: Programming Language :: Python :: 3.9
Classifier: Programming Language :: Python :: 3.10
Classifier: Programming Language :: Python :: 3.11
Requires-Dist: numpy
Requires-Dist: torch
Dynamic: author
Dynamic: author-email
Dynamic: classifier
Dynamic: description
Dynamic: description-content-type
Dynamic: home-page
Dynamic: license
Dynamic: requires-dist
Dynamic: summary
